runforrest.py
runforrest-0.4.3.dist-info/METADATA
runforrest-0.4.3.dist-info/WHEEL
runforrest-0.4.3.dist-info/top_level.txt
runforrest-0.4.3.dist-info/RECORD
