Metadata-Version: 2.1
Name: runforrest
Version: 0.4.3
Summary: Batch and run your code in parallel. Simply.
Home-page: https://github.com/bastibe/RunForrest
Author: Bastian Bechtold
Author-email: basti@bastibe.de
License: BSD 3-clause
Platform: UNKNOWN
Requires-Python: >=3.4
Requires-Dist: dill
